settings_vial/__init__.py
settings_vial/exceptions.py
settings_vial/settings_vial.py
settings_vial-0.2.0.dist-info/LICENSE
settings_vial-0.2.0.dist-info/METADATA
settings_vial-0.2.0.dist-info/WHEEL
settings_vial-0.2.0.dist-info/top_level.txt
settings_vial-0.2.0.dist-info/RECORD
