Metadata-Version: 2.1
Name: settings-vial
Version: 0.2.0
Summary: Python settings for cloud environments
Home-page: https://github.com/kpn/settings-vial
Author: Charles David de Moraes
Author-email: charles.moraes@kpn.com
License: Apache 2.0
Platform: UNKNOWN
Classifier: Development Status :: 3 - Alpha
Classifier: Environment :: Web Environment
Classifier: Intended Audience :: Developers
Classifier: Operating System :: OS Independent
Classifier: Programming Language :: Python
Classifier: Programming Language :: Python :: 3
Classifier: Programming Language :: Python :: 3.6
Classifier: Programming Language :: Python :: 3.7
Classifier: Topic :: Internet :: WWW/HTTP
Classifier: Topic :: Software Development :: Libraries :: Python Modules
Requires-Dist: python-dotenv (<1.0.0,>=0.10.3)
